IsoCon-0.3.2.data/scripts/IsoCon
IsoCon-0.3.2.dist-info/DESCRIPTION.rst
IsoCon-0.3.2.dist-info/METADATA
IsoCon-0.3.2.dist-info/RECORD
IsoCon-0.3.2.dist-info/WHEEL
IsoCon-0.3.2.dist-info/dependency_links.txt
IsoCon-0.3.2.dist-info/metadata.json
IsoCon-0.3.2.dist-info/top_level.txt
modules/SW_alignment_module.py
modules/__init__.py
modules/ccs_info.py
modules/correction_module.py
modules/edlib_alignment_module.py
modules/end_invariant_functions.py
modules/functions.py
modules/get_best_alignments.py
modules/graphs.py
modules/hypothesis_test_module.py
modules/isocon_get_candidates.py
modules/isocon_parameters.py
modules/isocon_statistical_test.py
modules/minimap_alignment_module.py
modules/nearest_neighbor_graph.py
modules/partitions.py
modules/input_output/__init__.py
modules/input_output/calc_memory.py
modules/input_output/fasta_parser.py
modules/input_output/fastq_parser.py
modules/input_output/write_output.py
