Metadata-Version: 2.0
Name: IsoCon
Version: 0.3.2
Summary: Pipeline for obtaining non-redundant haplotype specific transcript isoforms using PacBio IsoSeq reads.
Home-page: https://github.com/ksahlin/IsoCon
Author: Kristoffer Sahlin
Author-email: kxs624@psu.edu
License: UNKNOWN
Keywords: Iso-Seq CCS PacBio transcript long-read
Platform: UNKNOWN
Classifier: Development Status :: 3 - Alpha
Classifier: Programming Language :: Python :: 2.7
Classifier: Programming Language :: Python :: 3
Classifier: Programming Language :: Python :: 3.4
Classifier: Programming Language :: Python :: 3.5
Classifier: Programming Language :: Python :: 3.6
Requires-Python: >=2.7, !=3.0.*, !=3.1.*, !=3.2.*, !=3.3.*, <4
Requires-Dist: edlib (>=1.1.2)
Requires-Dist: pysam (>=0.11)
Requires-Dist: networkx (>=1.10)
Requires-Dist: parasail (>=1.1.11)
